pg_diff/__init__.py
pg_diff/pg_diff.py
pg_diff-0.2.1.dist-info/DESCRIPTION.rst
pg_diff-0.2.1.dist-info/METADATA
pg_diff-0.2.1.dist-info/RECORD
pg_diff-0.2.1.dist-info/WHEEL
pg_diff-0.2.1.dist-info/entry_points.txt
pg_diff-0.2.1.dist-info/metadata.json
pg_diff-0.2.1.dist-info/top_level.txt
pg_diff-0.2.1.dist-info/zip-safe
