Metadata-Version: 2.0
Name: pg-diff
Version: 0.2.1
Summary: a simple tool to diff schemas in two postgresql database
Home-page: https://github.com/hanks/pg_diff
Author: hanks
Author-email: zhouhan315@gmail.com
License: MIT License
Requires-Dist: deepdiff (>=2.5.1)
Requires-Dist: docopt (>=0.6.2)
Requires-Dist: psycopg2 (>=2.6.2)
Requires-Dist: schema (>=0.6.5)
